cmdstyler/__init__.py
cmdstyler/core.py
cmdstyler/cursor/__init__.py
cmdstyler/text/__init__.py
cmdstyler-0.2.2.dist-info/licenses/LICENSE
cmdstyler-0.2.2.dist-info/METADATA
cmdstyler-0.2.2.dist-info/WHEEL
cmdstyler-0.2.2.dist-info/top_level.txt
cmdstyler-0.2.2.dist-info/RECORD
