Metadata-Version: 2.4
Name: cmdstyler
Version: 0.2.2
Summary: Better CMD text utilities, uses the pdat file format
Author-email: Philipp Vukovic <philovic@outlook.de>
License: MIT License
Classifier: Programming Language :: Python :: 3
Classifier: License :: OSI Approved :: MIT License
Classifier: Operating System :: OS Independent
Classifier: Environment :: Console
Classifier: Topic :: Terminals
Classifier: Topic :: Utilities
Requires-Python: >=3.8
License-File: LICENSE
Requires-Dist: sty>=1.0.5
Requires-Dist: pyfiglet>=1.0.4
Dynamic: license-file
